pyaws/__init__.py
pyaws/__main__.py
pyaws/about_screen.py
pyaws/account_console_screen.py
pyaws/account_select_screen.py
pyaws/errors.py
pyaws/logger.py
pyaws/metadata_manager.py
pyaws/screen_manager.py
pyaws/settings_screen.py
pyaws/utils.py
pyaws/aws/__init__.py
pyaws/aws/__main__.py
pyaws/aws/ec2/__init__.py
pyaws/aws/ec2/ec2_commands.py
pyaws/aws/ec2/ec2_tables.py
pyaws/aws/iam/__init__.py
pyaws/aws/iam/iam_commands.py
pyaws/aws/iam/iam_tables.py
pyaws/aws/route53/__init__.py
pyaws/aws/route53/r53_commands.py
pyaws/aws/route53/r53_tables.py
pyaws/aws/secrets_manager/__init__.py
pyaws/aws/secrets_manager/sm_commands.py
pyaws/aws/systems_manager/__init__.py
pyaws/aws/systems_manager/ssm_commands.py
pyaws/aws/systems_manager/ssm_tables.py
pyaws_cui-0.0.1.dist-info/AUTHORS
pyaws_cui-0.0.1.dist-info/LICENSE
pyaws_cui-0.0.1.dist-info/METADATA
pyaws_cui-0.0.1.dist-info/WHEEL
pyaws_cui-0.0.1.dist-info/entry_points.txt
pyaws_cui-0.0.1.dist-info/top_level.txt
pyaws_cui-0.0.1.dist-info/RECORD
