Metadata-Version: 2.1
Name: pyaws_cui
Version: 0.0.1
Summary: AWS CUI Application
Author-email: James Lavender <careers@jameslavender.com>
Project-URL: Homepage, https://github.com/j-lavender/pyaws_cui
Project-URL: Issues, https://github.com/j-lavender/pyaws_cui/issues
Classifier: Programming Language :: Python
Classifier: Programming Language :: Python :: 3.9
Classifier: Programming Language :: Python :: 3.10
Classifier: Programming Language :: Python :: 3.11
Classifier: Programming Language :: Python :: 3.12
Classifier: Operating System :: OS Independent
Requires-Python: >=3.9
License-File: LICENSE
License-File: AUTHORS
Requires-Dist: boto3 ~=1.34.29
Requires-Dist: py-cui ==0.1.6
Requires-Dist: pyperclip ~=1.8.2
Requires-Dist: tabulate ~=0.9.0
Provides-Extra: all
Requires-Dist: npdoc2md ~=0.0.1 ; extra == 'all'
Provides-Extra: docs
Requires-Dist: npdoc2md ~=0.0.1 ; extra == 'docs'
